asset_loader/__init__.py
asset_loader/_main.py
asset_loader/py.typed
asset_loader-0.0.1.dist-info/METADATA
asset_loader-0.0.1.dist-info/WHEEL
asset_loader-0.0.1.dist-info/licenses/LICENSE
asset_loader-0.0.1.dist-info/RECORD
