Metadata-Version: 2.4
Name: asset-loader
Version: 0.0.1
Summary: Package for loading multiple assets of the same type in Python.
Project-URL: Homepage, https://github.com/Snowcaloid/py-asset-loader
Project-URL: Issues, https://github.com/Snowcaloid/py-asset-loader/issues
Author-email: Snowcaloid <dev.snowcaloid@gmail.com>
License-File: LICENSE
Classifier: Operating System :: OS Independent
Classifier: Programming Language :: Python :: 3
Requires-Python: >=3.13.2
Requires-Dist: bindable>=0.0.7
Requires-Dist: pyyaml>=6.0.2
